jass/agents/__init__.py
jass/agents/agent.py
jass/agents/agent_by_network.py
jass/agents/agent_cheating.py
jass/agents/agent_cheating_random_schieber.py
jass/agents/agent_random_schieber.py
jass/arena/__init__.py
jass/arena/arena.py
jass/arena/dealing_card_random_strategy.py
jass/arena/dealing_card_strategy.py
jass/game/__init__.py
jass/game/const.py
jass/game/game_observation.py
jass/game/game_rule.py
jass/game/game_sim.py
jass/game/game_state.py
jass/game/game_state_util.py
jass/game/game_util.py
jass/game/illegal_argument_error.py
jass/game/match.py
jass/game/rule_schieber.py
jass/logs/__init__.py
jass/logs/game_log_entry.py
jass/logs/game_obs_action_log_entry.py
jass/logs/log_entry_file_generator.py
jass/service/__init__.py
jass/service/player_service_app.py
jass/service/player_service_route.py
jass/train/__init__.py
jass/train/label_play.py
jass_kit-2.0.5.dist-info/LICENSE
jass_kit-2.0.5.dist-info/METADATA
jass_kit-2.0.5.dist-info/WHEEL
jass_kit-2.0.5.dist-info/top_level.txt
jass_kit-2.0.5.dist-info/RECORD
