Metadata-Version: 2.1
Name: jass-kit
Version: 2.0.5
Summary: Package for the game of jass
Home-page: 
Author: ABIZ HSLU
Author-email: thomas.koller@hslu.ch
Classifier: Programming Language :: Python :: 3
Classifier: Operating System :: OS Independent
Requires-Python: >=3.6
License-File: LICENSE
Requires-Dist: numpy
